CLA.md
CODE_OF_CONDUCT.md
CONTRIBUTING.md
MANIFEST.in
README.md
RELEASE_NOTES.md
requirements-test.txt
requirements.txt
setup.cfg
setup.py
meta1/__init__.py
meta1/account.py
meta1/amount.py
meta1/asset.py
meta1/block.py
meta1/blockchain.py
meta1/blockchainobject.py
meta1/committee.py
meta1/dex.py
meta1/exceptions.py
meta1/genesisbalance.py
meta1/htlc.py
meta1/instance.py
meta1/market.py
meta1/memo.py
meta1/message.py
meta1/meta1.py
meta1/notify.py
meta1/price.py
meta1/proposal.py
meta1/storage.py
meta1/transactionbuilder.py
meta1/utils.py
meta1/vesting.py
meta1/wallet.py
meta1/witness.py
meta1/worker.py
meta1.egg-info/PKG-INFO
meta1.egg-info/SOURCES.txt
meta1.egg-info/dependency_links.txt
meta1.egg-info/requires.txt
meta1.egg-info/top_level.txt
meta1api/__init__.py
meta1api/exceptions.py
meta1api/meta1noderpc.py
meta1api/websocket.py
meta1base/__init__.py
meta1base/account.py
meta1base/asset_permissions.py
meta1base/bip38.py
meta1base/chains.py
meta1base/memo.py
meta1base/objects.py
meta1base/objecttypes.py
meta1base/operationids.py
meta1base/operations.py
meta1base/signedtransactions.py
meta1base/transactions.py